ewokscore/__init__.py
ewokscore/bindings.py
ewokscore/dynamictask.py
ewokscore/engine.py
ewokscore/engine_interface.py
ewokscore/entry_points.py
ewokscore/hashing.py
ewokscore/inittask.py
ewokscore/methodtask.py
ewokscore/missing_data.py
ewokscore/model.py
ewokscore/node.py
ewokscore/notebooktask.py
ewokscore/ppftasks.py
ewokscore/progress.py
ewokscore/registration.py
ewokscore/scripttask.py
ewokscore/task.py
ewokscore/task_discovery.py
ewokscore/taskwithprogress.py
ewokscore/utils.py
ewokscore/variable.py
ewokscore/events/__init__.py
ewokscore/events/contexts.py
ewokscore/events/global_state.py
ewokscore/events/initialize_events.py
ewokscore/events/send_events.py
ewokscore/events/handlers/__init__.py
ewokscore/events/handlers/base.py
ewokscore/events/handlers/sqlite3.py
ewokscore/graph/__init__.py
ewokscore/graph/analysis.py
ewokscore/graph/compare.py
ewokscore/graph/error_handlers.py
ewokscore/graph/graph_io.py
ewokscore/graph/inputs.py
ewokscore/graph/models.py
ewokscore/graph/multigraph.py
ewokscore/graph/serialize.py
ewokscore/graph/subgraph.py
ewokscore/graph/taskgraph.py
ewokscore/graph/validate.py
ewokscore/graph/execute/__init__.py
ewokscore/graph/execute/sequential.py
ewokscore/graph/schema/__init__.py
ewokscore/graph/schema/metadata.py
ewokscore/graph/schema/update.py
ewokscore/persistence/__init__.py
ewokscore/persistence/atomic.py
ewokscore/persistence/file.py
ewokscore/persistence/json.py
ewokscore/persistence/nexus.py
ewokscore/persistence/proxy.py
ewokscore/tests/__init__.py
ewokscore/tests/conftest.py
ewokscore/tests/test_default_error_handlers.py
ewokscore/tests/test_dynamic_tasks.py
ewokscore/tests/test_events.py
ewokscore/tests/test_examples.py
ewokscore/tests/test_execute_graph.py
ewokscore/tests/test_graph.py
ewokscore/tests/test_graph_inputs.py
ewokscore/tests/test_graph_io.py
ewokscore/tests/test_graph_schema.py
ewokscore/tests/test_graph_serialize.py
ewokscore/tests/test_graph_start_end_nodes.py
ewokscore/tests/test_hashing.py
ewokscore-4.0.1.dist-info/licenses/LICENSE.md
ewokscore-4.0.1.dist-info/METADATA
ewokscore-4.0.1.dist-info/WHEEL
ewokscore-4.0.1.dist-info/entry_points.txt
ewokscore-4.0.1.dist-info/top_level.txt
ewokscore-4.0.1.dist-info/RECORD
