Metadata-Version: 2.4
Name: ewokscore
Version: 4.0.1
Summary: API for graphs and tasks in Ewoks
Author-email: ESRF <dau-pydev@esrf.fr>
License: # MIT License
Project-URL: Homepage, https://gitlab.esrf.fr/workflow/ewoks/ewokscore
Project-URL: Documentation, https://ewokscore.readthedocs.io/
Project-URL: Repository, https://gitlab.esrf.fr/workflow/ewoks/ewokscore
Project-URL: Issues, https://gitlab.esrf.fr/workflow/ewoks/ewokscore/issues/
Project-URL: Changelog, https://gitlab.esrf.fr/workflow/ewoks/ewokscore/-/blob/main/CHANGELOG.md
Keywords: ewoks
Classifier: Intended Audience :: Science/Research
Classifier: License :: OSI Approved :: MIT License
Classifier: Programming Language :: Python :: 3
Requires-Python: >=3.8
License-File: LICENSE.md
Requires-Dist: numpy>=1.15
Requires-Dist: networkx>=2
Requires-Dist: silx>=1
Requires-Dist: pyyaml>=5.1
Requires-Dist: h5py>=2.8
Requires-Dist: packaging
Requires-Dist: ewoksutils>=1.9.1
Requires-Dist: importlib_metadata; python_version < "3.9"
Requires-Dist: pydantic>=2
Provides-Extra: notebooks
Requires-Dist: papermill; extra == "notebooks"
Provides-Extra: test
Requires-Dist: ewokscore[notebooks]; extra == "test"
Requires-Dist: pytest>=7; extra == "test"
Requires-Dist: matplotlib>=3; extra == "test"
Requires-Dist: ipykernel; extra == "test"
Provides-Extra: dev
Requires-Dist: ewokscore[test]; extra == "dev"
Requires-Dist: black[jupyter]>=25; extra == "dev"
Requires-Dist: flake8>=4; extra == "dev"
Requires-Dist: flake8_nb>=0.3.1; extra == "dev"
Requires-Dist: isort; extra == "dev"
Provides-Extra: doc
Requires-Dist: ewokscore[test]; extra == "doc"
Requires-Dist: sphinx>=4.5; extra == "doc"
Requires-Dist: sphinxcontrib-mermaid>=0.7; extra == "doc"
Requires-Dist: sphinx-autodoc-typehints>=1.16; extra == "doc"
Requires-Dist: nbsphinx; extra == "doc"
Requires-Dist: docutils<0.21; extra == "doc"
Requires-Dist: nbsphinx_link; extra == "doc"
Requires-Dist: pydata-sphinx-theme; extra == "doc"
Requires-Dist: sphinx-copybutton; extra == "doc"
Dynamic: license-file
